{"nodes": [{"id": "c_projet_lency_saas_lency_src_front_hooks_use_viewport_recently_viewed_ts", "label": "use-viewport-recently-viewed.ts", "file_type": "code", "source_file": "C:\\Projet\\Lency - SaaS\\Lency\\src\\front\\hooks\\use-viewport-recently-viewed.ts", "source_location": "L1"}, {"id": "hooks_use_viewport_recently_viewed_useviewportrecentlyviewed", "label": "useViewportRecentlyViewed()", "file_type": "code", "source_file": "C:\\Projet\\Lency - SaaS\\Lency\\src\\front\\hooks\\use-viewport-recently-viewed.ts", "source_location": "L7"}], "edges": [{"source": "c_projet_lency_saas_lency_src_front_hooks_use_viewport_recently_viewed_ts", "target": "react", "relation": "imports_from", "context": "import", "confidence": "EXTRACTED", "source_file": "C:\\Projet\\Lency - SaaS\\Lency\\src\\front\\hooks\\use-viewport-recently-viewed.ts", "source_location": "L3", "weight": 1.0}, {"source": "c_projet_lency_saas_lency_src_front_hooks_use_viewport_recently_viewed_ts", "target": "c_projet_lency_saas_lency_src_front_stores_use_recently_viewed_store_ts", "relation": "imports_from", "context": "import", "confidence": "EXTRACTED", "source_file": "C:\\Projet\\Lency - SaaS\\Lency\\src\\front\\hooks\\use-viewport-recently-viewed.ts", "source_location": "L4", "weight": 1.0}, {"source": "c_projet_lency_saas_lency_src_front_hooks_use_viewport_recently_viewed_ts", "target": "stores_use_recently_viewed_store_userecentlyviewed", "relation": "imports", "context": "import", "confidence": "EXTRACTED", "source_file": "C:\\Projet\\Lency - SaaS\\Lency\\src\\front\\hooks\\use-viewport-recently-viewed.ts", "source_location": "L4", "weight": 1.0}, {"source": "c_projet_lency_saas_lency_src_front_hooks_use_viewport_recently_viewed_ts", "target": "c_projet_lency_saas_lency_src_front_types_post_schema_ts", "relation": "imports_from", "context": "import", "confidence": "EXTRACTED", "source_file": "C:\\Projet\\Lency - SaaS\\Lency\\src\\front\\hooks\\use-viewport-recently-viewed.ts", "source_location": "L5", "weight": 1.0}, {"source": "c_projet_lency_saas_lency_src_front_hooks_use_viewport_recently_viewed_ts", "target": "types_post_schema_postwithuserstate", "relation": "imports", "context": "import", "confidence": "EXTRACTED", "source_file": "C:\\Projet\\Lency - SaaS\\Lency\\src\\front\\hooks\\use-viewport-recently-viewed.ts", "source_location": "L5", "weight": 1.0}, {"source": "c_projet_lency_saas_lency_src_front_hooks_use_viewport_recently_viewed_ts", "target": "hooks_use_viewport_recently_viewed_useviewportrecentlyviewed", "relation": "contains", "confidence": "EXTRACTED", "source_file": "C:\\Projet\\Lency - SaaS\\Lency\\src\\front\\hooks\\use-viewport-recently-viewed.ts", "source_location": "L7", "weight": 1.0}], "raw_calls": [{"caller_nid": "hooks_use_viewport_recently_viewed_useviewportrecentlyviewed", "callee": "useRecentlyViewed", "is_member_call": false, "source_file": "C:\\Projet\\Lency - SaaS\\Lency\\src\\front\\hooks\\use-viewport-recently-viewed.ts", "source_location": "L8"}, {"caller_nid": "hooks_use_viewport_recently_viewed_useviewportrecentlyviewed", "callee": "useRef", "is_member_call": false, "source_file": "C:\\Projet\\Lency - SaaS\\Lency\\src\\front\\hooks\\use-viewport-recently-viewed.ts", "source_location": "L9"}, {"caller_nid": "hooks_use_viewport_recently_viewed_useviewportrecentlyviewed", "callee": "useRef", "is_member_call": false, "source_file": "C:\\Projet\\Lency - SaaS\\Lency\\src\\front\\hooks\\use-viewport-recently-viewed.ts", "source_location": "L10"}, {"caller_nid": "hooks_use_viewport_recently_viewed_useviewportrecentlyviewed", "callee": "useRef", "is_member_call": false, "source_file": "C:\\Projet\\Lency - SaaS\\Lency\\src\\front\\hooks\\use-viewport-recently-viewed.ts", "source_location": "L11"}, {"caller_nid": "hooks_use_viewport_recently_viewed_useviewportrecentlyviewed", "callee": "useRef", "is_member_call": false, "source_file": "C:\\Projet\\Lency - SaaS\\Lency\\src\\front\\hooks\\use-viewport-recently-viewed.ts", "source_location": "L12"}, {"caller_nid": "hooks_use_viewport_recently_viewed_useviewportrecentlyviewed", "callee": "useEffect", "is_member_call": false, "source_file": "C:\\Projet\\Lency - SaaS\\Lency\\src\\front\\hooks\\use-viewport-recently-viewed.ts", "source_location": "L14"}, {"caller_nid": "hooks_use_viewport_recently_viewed_useviewportrecentlyviewed", "callee": "useEffect", "is_member_call": false, "source_file": "C:\\Projet\\Lency - SaaS\\Lency\\src\\front\\hooks\\use-viewport-recently-viewed.ts", "source_location": "L15"}, {"caller_nid": "hooks_use_viewport_recently_viewed_useviewportrecentlyviewed", "callee": "useEffect", "is_member_call": false, "source_file": "C:\\Projet\\Lency - SaaS\\Lency\\src\\front\\hooks\\use-viewport-recently-viewed.ts", "source_location": "L17"}]}